LICENSE
README.md
setup.py
src/keypact/__init__.py
src/keypact/keypact.py
src/keypact.egg-info/PKG-INFO
src/keypact.egg-info/SOURCES.txt
src/keypact.egg-info/dependency_links.txt
src/keypact.egg-info/entry_points.txt
src/keypact.egg-info/not-zip-safe
src/keypact.egg-info/requires.txt
src/keypact.egg-info/top_level.txt