Metadata-Version: 2.1
Name: keypact
Version: 0.1.0
Summary: Efficient Key-Value Data Storage with Multithreaded Simultaneous Writing
Home-page: https://github.com/onuratakan/KeyPact
Author: Onur Atakan ULUSOY
Author-email: atadogan06@gmail.com
License: MIT
Platform: UNKNOWN
Requires-Python: >= 3
